{
  "setting": {},
  "condition": {
    "plugin": {
      "list": []
    },
    "game": {
      "list": []
    },
    "gamePlugin": {
      "list": []
    },
    "miniprogram": {
      "list": [
        {
          "name": "pages/lottery-9/index",
          "pathName": "pages/lottery-9/index",
          "query": "",
          "scene": null
        },
        {
          "name": "pages/lottery-17/index",
          "pathName": "pages/lottery-17/index",
          "query": "",
          "scene": null
        },
        {
          "name": "pages/lottery-18/index",
          "pathName": "pages/lottery-18/index",
          "query": "",
          "scene": null
        }
      ]
    }
  }
}